{"status":"OK","request_id":"cc942c9c-3eed-46ae-8863-36641a00e3a5","parameters":{"query":"golang jobs in nigeria","page":1,"num_pages":3,"country":"ng","language":"en"},"data":[{"job_id":"2qGahqIc_VQakKV9AAAAAA==","job_title":"Golang Software Engineer, Commercial Systems","employer_name":"Canonical","employer_logo":"https://encrypted-tbn0.gstatic.com/images?q=tbn:ANd9GcTN1rp9LyuqGEsp4IjSXeT87xSmDDw64mG1SWLF&s=0","employer_website":"https://canonical.com","job_publisher":"LinkedIn Nigeria","job_employment_type":"Full-time","job_employment_types":["FULLTIME"],"job_apply_link":"https://ng.linkedin.com/jobs/view/golang-software-engineer-commercial-systems-at-canonical-4189621000?utm_campaign=google_jobs_apply&utm_source=google_jobs_apply&utm_medium=organic","job_apply_is_direct":false,"apply_options":[{"publisher":"LinkedIn Nigeria","apply_link":"https://ng.linkedin.com/jobs/view/golang-software-engineer-commercial-systems-at-canonical-4189621000?utm_campaign=google_jobs_apply&utm_source=google_jobs_apply&utm_medium=organic","is_direct":false}],"job_description":"Canonical is a leading provider of open-source software and operating systems for global enterprise and technology markets. Our platform, Ubuntu, is very widely used in breakthrough enterprise initiatives such as public cloud, data science, AI, engineering innovation and IoT. Our customers include the world's leading public cloud and silicon providers, and industry leaders in many sectors. The company is a pioneer of global distributed collaboration, with 1200+ colleagues in more than 80 countries and very few office-based roles. Teams meet two to four times yearly in person, in interesting locations around the world, to align on strategy and execution.\n\nThe company is founder led, profitable and growing.\n\nWe are hiring a Golang Software Engineer at any seniority level, who strives for the highest engineering quality, seeks improvements, continuously develops their skills, and applies them at work. This is an exciting opportunity to work with many popular software systems, integrations technologies, and exciting open source solutions.\n\nThe Commercial Systems unit is conceived as five engineering teams that closely collaborate with other engineering and business teams at Canonical. Services designed, developed, and operated by the Commercial Systems unit are at the heart of Canonical business and Golang plays an integral role in it. We are looking for software engineers for these teams:\n\nThe Billing team designs, develops, and operates a Golang service that provides a standardized and scalable capability to turn metrics into billable amounts, enable customers to see their current spend with Canonical at any time, and ensure accurate, reliable, and timely billing. The service further integrates with other engineering, business, payment systems. This team is an excellent match for any software engineer interested in growing their skills in the billing and payment processing domain.\n\nThe Contracts team designs, develops, and operates a Golang service that will become the single source of truth for all contracts with all customers. The service provides a standardized CPQ capability and stores signed contracts in a structured format. The service further integrates with other engineering and business systems including a CRM system and an accounting system. This team is an excellent match for any software engineer interested in understanding sales and revenue processes and growing their skills beyond software engineering.\n\nThe Livepatch team designs and develops a service for the delivery of Linux kernel patches to shrink the exploit window for critical and high severity Linux kernel vulnerabilities, by patching the Linux kernel between security maintenance windows, while the system runs. The engineering team behind this product develops Golang based client and backend components, while another Canonical team, the Kernel team, develops the security patches. This team is a great opportunity for a software engineer interested in security and with a strong focus on engineering quality and reliability.\n\nLocation: This role will be based remotely in the EMEA region.\n\nThe role entails\n• Develop engineering solutions leveraging Golang\n• Collaborate with colleagues on technical designs and code reviews\n• Deploy and operate services developed by the team\n• Depending on your seniority, coach, mentor, and offer career development feedback\n• Develop and evangelize great engineering and organizational practices\n\nWhat we are looking for in you\n• Exceptional academic track record from both high school and university\n• Undergraduate degree in a technical subject or a compelling narrative about your alternative chosen path\n• Track record of going above-and-beyond expectations to achieve outstanding results\n• Experience with software development in Golang\n• Professional written and spoken English with excellent presentation skills\n• Result-oriented, with a personal drive to meet commitments\n• Ability to travel internationally twice a year, for company events up to two weeks long\n\nNice-to-have skills\n• Performance engineering and security experience\n• Experience with accounting, sales, sales operations, or other business roles\n\nWhat we offer colleagues\n\nWe consider geographical location, experience, and performance in shaping compensation worldwide. We revisit compensation annually (and more often for graduates and associates) to ensure we recognize outstanding performance. In addition to base pay, we offer a performance-driven annual bonus or commission. We provide all team members with additional benefits, which reflect our values and ideals. We balance our programs to meet local needs and ensure fairness globally.\n• Distributed work environment with twice-yearly team sprints in person\n• Personal learning and development budget of USD 2,000 per year\n• Annual compensation review\n• Recognition rewards\n• Annual holiday leave\n• Maternity and paternity leave\n• Employee Assistance Program\n• Opportunity to travel to new locations to meet colleagues\n• Priority Pass, and travel upgrades for long haul company events\n\nAbout Canonical\n\nCanonical is a pioneering tech firm at the forefront of the global move to open source. As the company that publishes Ubuntu, one of the most important open source projects and the platform for AI, IoT and the cloud, we are changing the world of software. We recruit on a global basis and set a very high standard for people joining the company. We expect excellence - in order to succeed, we need to be the best at what we do. Most colleagues at Canonical have worked from home since its inception in 2004. Working here is a step into the future, and will challenge you to think differently, work smarter, learn new skills, and raise your game.\n\nCanonical is an equal opportunity employer\n\nWe are proud to foster a workplace free from discrimination. Diversity of experience, perspectives, and background create a better work environment and better products. Whatever your identity, we will give your application fair consideration.","job_is_remote":false,"job_posted_at":"8 days ago","job_posted_at_timestamp":1742428800,"job_posted_at_datetime_utc":"2025-03-20T00:00:00.000Z","job_location":"Lagos","job_city":"Lagos","job_state":"Lagos","job_country":"NG","job_latitude":6.5243793,"job_longitude":3.3792057,"job_benefits":null,"job_google_link":"https://www.google.com/search?q=jobs&gl=ng&hl=en&udm=8#vhid=vt%3D20/docid%3D2qGahqIc_VQakKV9AAAAAA%3D%3D&vssid=jobs-detail-viewer","job_salary":null,"job_min_salary":null,"job_max_salary":null,"job_salary_period":null,"job_highlights":{},"job_onet_soc":"15113200","job_onet_job_zone":"4"},{"job_id":"L6jh_fG1DD7nZ4BkAAAAAA==","job_title":"Golang Engineer","employer_name":"Canonical","employer_logo":"https://encrypted-tbn0.gstatic.com/images?q=tbn:ANd9GcTN1rp9LyuqGEsp4IjSXeT87xSmDDw64mG1SWLF&s=0","employer_website":"https://canonical.com","job_publisher":"LinkedIn","job_employment_type":"Full-time","job_employment_types":["FULLTIME"],"job_apply_link":"https://ng.linkedin.com/jobs/view/golang-engineer-at-canonical-4189618203?utm_campaign=google_jobs_apply&utm_source=google_jobs_apply&utm_medium=organic","job_apply_is_direct":false,"apply_options":[{"publisher":"LinkedIn","apply_link":"https://ng.linkedin.com/jobs/view/golang-engineer-at-canonical-4189618203?utm_campaign=google_jobs_apply&utm_source=google_jobs_apply&utm_medium=organic","is_direct":false}],"job_description":"This is our general process for Golang engineers of all levels of seniority, for all relevant teams at Canonical. Apply here if you are an exceptional software engineer who prefers to work in Go. After the first round of interviews we'll find the best fit product team at Canonical for you to progress your application based on your personal interests.\n\nCanonical prefers Golang for software where performance and security are primary considerations. We also have substantial projects in Python, C, C++ and are starting to invest in Rust. For front-end development we prefer React and Flutter.\n\nGolang is an essential language for our engineering teams, who build the systems that deliver Ubuntu to the world. From our software distribution systems, to those which build and test every possible kind of open source on every architecture, from our systems management tools to our distributed systems operations R&D, we count on Golang for its tasteful concurrency and developer ecosystem. Juju, Livepatch, LXD, MAAS, Microk8s, Snapd, Ubuntu Core, Ubuntu Pro, and many more Canonical offerings include Golang components.\n\nWe also want to ensure that Ubuntu is the very best platform for Golang development, offering easy access to the widest range of tooling and capabilities that support cutting edge open source and enterprise development.\n\nJoin us in our mission to deliver innovative open-source solutions to individuals and enterprises around the world. We expect the highest engineering standards and strong motivation to get things done well in a fully remote and distributed environment. These roles require extensive personal experience with Linux - the more different versions of Linux the better!\n\nLocation: we have open roles for Golang engineers in every time zone\n\nThe role entails\n• Design and implement well-tested and documented software in Go\n• Debug and fix issues encountered by your users\n• Participate in our engineering process through code and architectural reviews\n• Collaborate with community and colleagues on technical specifications\n• Seek improvements to engineering and operations practices\n• In some cases, deploy and operate services developed by the team\n• Contribute to the success of your product through technical advocacy\n\nWhat we are looking for in you\n• An exceptional academic track record from both high school and university\n• Undergraduate degree in Computer Science or STEM, or a compelling narrative about your alternative path\n• Drive and a track record of going above-and-beyond expectations\n• Well-organized, self-starting and able to deliver to schedule\n• Professional manner interacting with colleagues, partners, and community\n• Experience designing and writing high-quality Golang software on Linux\n• Experience with and passion for Linux at the system level\n• For more senior roles, experience building, deploying, and operating distributed systems and APIs\n• Professional written and spoken English\n• Experience with Linux (Debian or Ubuntu preferred)\n• Excellent interpersonal skills, curiosity, flexibility, and accountability\n• Passion, thoughtfulness, and self-motivation\n• Excellent communication and presentation skills\n• Result-oriented, with a personal drive to meet commitments\n• Ability to travel twice a year, for company events up to two weeks each\n\nNice-to-have skills\n• Experience developing for Ubuntu Linux\n• Experience with Juju, LXD, Microk8s, Snapd, Ubuntu Core, Ubuntu Pro\n• Performance engineering and security experience\n\nWhat we offer colleagues\n\nWe consider geographical location, experience, and performance in shaping compensation worldwide. We revisit compensation annually (and more often for graduates and associates) to ensure we recognize outstanding performance. In addition to base pay, we offer a performance-driven annual bonus or commission. We provide all team members with additional benefits, which reflect our values and ideals. We balance our programs to meet local needs and ensure fairness globally.\n• Distributed work environment with twice-yearly team sprints in person\n• Personal learning and development budget of USD 2,000 per year\n• Annual compensation review\n• Recognition rewards\n• Annual holiday leave\n• Maternity and paternity leave\n• Employee Assistance Program\n• Opportunity to travel to new locations to meet colleagues\n• Priority Pass, and travel upgrades for long haul company events\n\nAbout Canonical\n\nCanonical is a pioneering tech firm at the forefront of the global move to open source. As the company that publishes Ubuntu, one of the most important open source projects and the platform for AI, IoT and the cloud, we are changing the world of software. We recruit on a global basis and set a very high standard for people joining the company. We expect excellence - in order to succeed, we need to be the best at what we do. Most colleagues at Canonical have worked from home since its inception in 2004. Working here is a step into the future, and will challenge you to think differently, work smarter, learn new skills, and raise your game.\n\nCanonical is an equal opportunity employer\n\nWe are proud to foster a workplace free from discrimination. Diversity of experience, perspectives, and background create a better work environment and better products. Whatever your identity, we will give your application fair consideration.","job_is_remote":false,"job_posted_at":"8 days ago","job_posted_at_timestamp":1742428800,"job_posted_at_datetime_utc":"2025-03-20T00:00:00.000Z","job_location":"Lagos","job_city":"Lagos","job_state":"Lagos","job_country":"NG","job_latitude":6.5243793,"job_longitude":3.3792057,"job_benefits":null,"job_google_link":"https://www.google.com/search?q=jobs&gl=ng&hl=en&udm=8#vhid=vt%3D20/docid%3DL6jh_fG1DD7nZ4BkAAAAAA%3D%3D&vssid=jobs-detail-viewer","job_salary":null,"job_min_salary":null,"job_max_salary":null,"job_salary_period":null,"job_highlights":{},"job_onet_soc":"15113200","job_onet_job_zone":"4"},{"job_id":"vSYWtSN_SSqn9q8aAAAAAA==","job_title":"Go (Golang) Software Engineer for Identity Management","employer_name":"Canonical","employer_logo":"https://encrypted-tbn0.gstatic.com/images?q=tbn:ANd9GcTN1rp9LyuqGEsp4IjSXeT87xSmDDw64mG1SWLF&s=0","employer_website":"https://canonical.com","job_publisher":"LinkedIn Nigeria","job_employment_type":"Full-time","job_employment_types":["FULLTIME"],"job_apply_link":"https://ng.linkedin.com/jobs/view/go-golang-software-engineer-for-identity-management-at-canonical-4170105887?utm_campaign=google_jobs_apply&utm_source=google_jobs_apply&utm_medium=organic","job_apply_is_direct":false,"apply_options":[{"publisher":"LinkedIn Nigeria","apply_link":"https://ng.linkedin.com/jobs/view/go-golang-software-engineer-for-identity-management-at-canonical-4170105887?utm_campaign=google_jobs_apply&utm_source=google_jobs_apply&utm_medium=organic","is_direct":false}],"job_description":"Summary\n\nThis is an exciting opportunity for an experienced software engineer passionate about open source software, Linux, and Web Services at scale. Come build a rewarding, meaningful career working with the best and brightest people in technology at Canonical, a growing international software company.\n\nBring your Go (Golang) and Python skills to bear on identity, authorization and access management across Canonical's suite of enterprise products and web services.\n\nAs a software engineer for Identity Management products of Canonical, you will modernize and expand the capabilities of the identity management solutions we use for authentication and authorization in our products, as well as our canonical.com and ubuntu.com websites. Your work on Identity Management will directly impact the users of all Canonical products.\n\nTechnical excellence and a background in software engineering are necessary prerequisites for this role. You will be expected to own the design and delivery of the system, facilitate integrations and work with your team on strategy and execution.\n\nWhat you'll do\n• Collaborate proactively with a distributed team\n• Write clean web service APIs to support both CLI and web frontend clients, using Go (Golang) and optionally Python\n• Design and implement new features and enhancements from spec to production and ongoing operations at scale\n• Review code produced by other engineers\n• Discuss ideas and collaborate on finding good solutions\n• Create and enhance management, authentication and authorization API endpoints\n• Craft end-user authentication flows from design to implementation\n• Modernize the identity stack of our websites and products by driving adoption of best-of-breed IAM technologies\n• Deliver great products that users love by maintaining a culture of quality and engineering excellence\n• Work from home with global travel 2 to 4 weeks per year for internal and external events\n\nWho you are\n• You have a Bachelor's or equivalent in Computer Science, STEM or similar degree\n• You are a software engineer, with specific experience building identity and access management products\n• You are familiar with the open source software, standards, protocols and concepts in the identity space (e.g. OpenID, OAuth, LDAP)\n• You have experience implementing authorization frameworks in distributed systems\n• You value secure coding and standards, and enjoy working on teams that do the same\n• You have solid experience working in an agile development environment\n• You love technology and working with a diverse set of talented people\n• You are comfortable with Ubuntu as a development and deployment platform\n• You are curious, flexible, articulate, and accountable\n• You value soft skills and are passionate, enterprising, thoughtful, and self-motivated\n• You love embracing new technologies and pushing the boundaries of what is possible, with a view to building products that improve how people operate software and infrastructure everywhere\n\nAbout Canonical\n\nCanonical is a growing, international software company that works with the open-source community to deliver Ubuntu -- the world's #1 cloud operating system. Our mission is to realise the potential of free software in the lives of individuals and organisations. Our services are helping businesses worldwide to reduce costs, improve efficiency and enhance security with Ubuntu. Canonical is a unique tech company - global, remote-first, open source, with 700 professionals across 50 countries - we want to be the world's best, not biggest, global software company. With almost every team remote by default, Canonical sets the pace on the 21st-century digital workplace.\n\nWhat Canonical offers:\n• Work from home\n• Learning and development allowances\n• Competitive Salary\n• Annual compensation review\n• Recognition rewards\n• Generous annual leave\n• Paid maternity, paternity and sick leave\n• Priority Pass for travel\n• Exposure to international business and technology\n\nWe are proud to foster a workplace free from discrimination. Diversity of experience, perspectives, and background create a better work environment and better products. Whatever your identity we will give your application fair consideration.\n\n#stack","job_is_remote":false,"job_posted_at":"29 days ago","job_posted_at_timestamp":1740614400,"job_posted_at_datetime_utc":"2025-02-27T00:00:00.000Z","job_location":"Lagos","job_city":"Lagos","job_state":"Lagos","job_country":"NG","job_latitude":6.5243793,"job_longitude":3.3792057,"job_benefits":null,"job_google_link":"https://www.google.com/search?q=jobs&gl=ng&hl=en&udm=8#vhid=vt%3D20/docid%3DvSYWtSN_SSqn9q8aAAAAAA%3D%3D&vssid=jobs-detail-viewer","job_salary":null,"job_min_salary":null,"job_max_salary":null,"job_salary_period":null,"job_highlights":{},"job_onet_soc":"15113200","job_onet_job_zone":"4"},{"job_id":"tAI2Pm9JjyxhdXVGAAAAAA==","job_title":"Golang System Software Engineer - Containers / Virtualisation at Canonical Nigeria (Remote)","employer_name":"Canonical Nigeria (Remote)","employer_logo":null,"employer_website":"https://www.hotnigerianjobs.com","job_publisher":"Jooble","job_employment_type":"Full-time","job_employment_types":["FULLTIME"],"job_apply_link":"https://ng.jooble.org/jdp/-3364346516210287361?utm_campaign=google_jobs_apply&utm_source=google_jobs_apply&utm_medium=organic","job_apply_is_direct":false,"apply_options":[{"publisher":"Jooble","apply_link":"https://ng.jooble.org/jdp/-3364346516210287361?utm_campaign=google_jobs_apply&utm_source=google_jobs_apply&utm_medium=organic","is_direct":false},{"publisher":"LinkedIn","apply_link":"https://ng.linkedin.com/jobs/view/golang-system-software-engineer-containers-virtualisation-at-canonical-4185054552?utm_campaign=google_jobs_apply&utm_source=google_jobs_apply&utm_medium=organic","is_direct":false}],"job_description":"We are recruiting to fill the position below:\nJob Title: Golang System Software Engineer – Containers / Virtualisation\n\nLocation: Lagos\nEmployment Type: Full-time","job_is_remote":false,"job_posted_at":"11 days ago","job_posted_at_timestamp":1742169600,"job_posted_at_datetime_utc":"2025-03-17T00:00:00.000Z","job_location":"Nigeria","job_city":null,"job_state":null,"job_country":"NG","job_latitude":9.081999,"job_longitude":8.675277,"job_benefits":null,"job_google_link":"https://www.google.com/search?q=jobs&gl=ng&hl=en&udm=8#vhid=vt%3D20/docid%3DtAI2Pm9JjyxhdXVGAAAAAA%3D%3D&vssid=jobs-detail-viewer","job_salary":null,"job_min_salary":null,"job_max_salary":null,"job_salary_period":null,"job_highlights":{},"job_onet_soc":"15113200","job_onet_job_zone":"4"},{"job_id":"bbsXuyeVh4LaHGTlAAAAAA==","job_title":"Golang Engineer - Canonical Nigeria","employer_name":"Canonical Nigeria","employer_logo":null,"employer_website":null,"job_publisher":"BetaJob","job_employment_type":"Full-time","job_employment_types":["FULLTIME"],"job_apply_link":"https://betajob.com.ng/golang-engineer-canonical-nigeria/26293?utm_campaign=google_jobs_apply&utm_source=google_jobs_apply&utm_medium=organic","job_apply_is_direct":true,"apply_options":[{"publisher":"BetaJob","apply_link":"https://betajob.com.ng/golang-engineer-canonical-nigeria/26293?utm_campaign=google_jobs_apply&utm_source=google_jobs_apply&utm_medium=organic","is_direct":true}],"job_description":"We are recruiting to fill the position below: Job Title: Golang Engineer Location: Lagos Job type: Full-time Description This is our general process for Golang engineers of all levels of seniority, for all relevant teams at Canonical. Apply here if you are an exceptional software engineer who prefers to work in Go. After the first round of interviews we’ll find the best fit product team at Canonical for you to progress your application based on your personal interests. Canonical prefers Golang for software where performance and security are primary considerations. We also have substantial projects in Python, C, C++ and are starting to invest in Rust. For front-end development we prefer React and Flutter. Golang is an essential language for our engineering teams, who build the systems that deliver Ubuntu to the world. From our software distribution systems, to those which build and test every possible kind of open source on every architecture, from our systems management tools to our distributed systems operations R&D, we count on Golang for its tasteful concurrency and developer ecosystem. Juju, Livepatch, LXD, MAAS, Microk8s, Snapd, Ubuntu Core, Ubuntu Pro, and many more Canonical offerings include Golang components. We also want to ensure that Ubuntu is the very best platform for Golang development, offering easy access to the widest range of tooling and capabilities that support cutting edge open source and enterprise development. Join us in our mission to deliver innovative open-source solutions to individuals and enterprises around the world. We expect the highest engineering standards and strong motivation to get things done well in a fully remote and distributed environment. These roles require extensive personal experience with Linux - the more different versions of Linux the better! Location: we have open roles for Golang engineers in every time zone Responsibilities What your day will look like: Design and implement well-tested and documented software in Go Debug and fix issues encountered by your users Participate in our engineering process through code and architectural reviews Collaborate with community and colleagues on technical specifications Seek improvements to engineering and operations practices In some cases, deploy and operate services developed by the team Contribute to the success of your product through technical advocacy Requirements What we are looking for in you: An exceptional academic track record from both high school and university Undergraduate Degree in Computer Science or STEM, or a compelling narrative about your alternative path Drive and a track record of going above-and-beyond expectations Well-organised, self-starting and able to deliver to schedule Professional manner interacting with colleagues, partners, and community Experience designing and writing high-quality Golang software on Linux Experience with and passion for Linux at the system level For more senior roles, experience building, deploying, and operating distributed systems and APIs Professional written and spoken English Experience with Linux (Debian or Ubuntu preferred) Excellent interpersonal skills, curiosity, flexibility, and accountability Passion, thoughtfulness, and self-motivation Excellent communication and presentation skills Result-oriented, with a personal drive to meet commitments Ability to travel twice a year, for company events up to two weeks each Additional skills that you might also bring: Experience developing for Ubuntu Linux Experience with Juju, LXD, Microk8s, Snapd, Ubuntu Core, Ubuntu Pro Performance engineering and security experience What we offer you We consider geographical location, experience, and performance in shaping compensation worldwide. We revisit compensation annually (and more often for graduates and associates) to ensure we recognise outstanding performance. In addition to base pay, we offer a performance-driven annual bonus. We provide all team members with additional benefits, which reflect our values and ideals. We balance our programs to meet local needs and ensure fairness globally. Distributed work environment with twice-yearly team sprints in person Personal learning and development budget of USD 2,000 per year Annual compensation review Recognition rewards Annual holiday leave Maternity and paternity leave Employee Assistance Programme Opportunity to travel to new locations to meet colleagues Priority Pass, and travel upgrades for long haul company events. Application Closing Date Not Specified. How to Apply Interested and qualified candidates should: Click below to apply;","job_is_remote":false,"job_posted_at":null,"job_posted_at_timestamp":null,"job_posted_at_datetime_utc":null,"job_location":"Lagos","job_city":"Lagos","job_state":"Lagos","job_country":"NG","job_latitude":6.5243793,"job_longitude":3.3792057,"job_benefits":null,"job_google_link":"https://www.google.com/search?q=jobs&gl=ng&hl=en&udm=8#vhid=vt%3D20/docid%3DbbsXuyeVh4LaHGTlAAAAAA%3D%3D&vssid=jobs-detail-viewer","job_salary":null,"job_min_salary":null,"job_max_salary":null,"job_salary_period":null,"job_highlights":{},"job_onet_soc":"15113200","job_onet_job_zone":"4"},{"job_id":"n-7kktQ0ACd7EQe6AAAAAA==","job_title":"GoLang Developer at Acronis","employer_name":"Acronis","employer_logo":null,"employer_website":"https://www.acronis.com","job_publisher":"JobNetworkNigeria","job_employment_type":"Full-time","job_employment_types":["FULLTIME"],"job_apply_link":"https://jobnetworknigeria.com/job/golang-developer-at-acronis/?utm_campaign=google_jobs_apply&utm_source=google_jobs_apply&utm_medium=organic","job_apply_is_direct":true,"apply_options":[{"publisher":"JobNetworkNigeria","apply_link":"https://jobnetworknigeria.com/job/golang-developer-at-acronis/?utm_campaign=google_jobs_apply&utm_source=google_jobs_apply&utm_medium=organic","is_direct":true}],"job_description":"Acronis is revolutionizing cyber protection by unifying backup, disaster recovery, storage, next-generation anti-malware, and protection management into one solution. This all-in-one integration removes the complexity and risks associated with non-integrated solutions and offers easy, complete and reliable data protection for all workloads, applications, and systems across any environment—all at a low and predictable cost.\n\nJob Position: GoLang Developer (Advanced Automation)\n\nJob Location: Abuja, Nigeria\n\nJob Responsibilities\n• Analyse, research and develop functionality to roadmap requirements;\n• Participate in design and peer code reviews.\n• Develop unit tests and planform features;\n• Support QA team in technical matters;\n• Overlook deployments and maintain the code after it’s deployed.\n\nJob Requirements\n• At least 3 years of experience writing well-designed, high-quality production code\n• Solid knowledge and experience with GoLang, JavaScript\n• Experience with databases (MySQL or PostgreSQL)\n• Knowledge of the principles of REST / RESTful\n• Strong knowledge of software implementation best practices\n• Knowledge of MSSQL, stored procedures, and/or C# will be a plus\n• Good interpersonal, written and verbal communication skills\n• Fluent English\n\nHow to Apply\n\nInterested and qualified candidates should:\n\nClick here to apply online\n\nTagged as: Information Technology","job_is_remote":false,"job_posted_at":null,"job_posted_at_timestamp":null,"job_posted_at_datetime_utc":null,"job_location":"Abuja","job_city":"Abuja","job_state":"Federal Capital Territory","job_country":"NG","job_latitude":9.0562646,"job_longitude":7.4985259,"job_benefits":null,"job_google_link":"https://www.google.com/search?q=jobs&gl=ng&hl=en&udm=8#vhid=vt%3D20/docid%3Dn-7kktQ0ACd7EQe6AAAAAA%3D%3D&vssid=jobs-detail-viewer","job_salary":null,"job_min_salary":null,"job_max_salary":null,"job_salary_period":null,"job_highlights":{},"job_onet_soc":"15113200","job_onet_job_zone":"4"},{"job_id":"L1WPUgTztny5rIYDAAAAAA==","job_title":"Software Engineer - Python/Golang - Kubernetes","employer_name":"Canonical","employer_logo":"https://encrypted-tbn0.gstatic.com/images?q=tbn:ANd9GcTN1rp9LyuqGEsp4IjSXeT87xSmDDw64mG1SWLF&s=0","employer_website":"https://canonical.com","job_publisher":"LinkedIn Nigeria","job_employment_type":"Full-time","job_employment_types":["FULLTIME"],"job_apply_link":"https://ng.linkedin.com/jobs/view/software-engineer-python-golang-kubernetes-at-canonical-4185055524?utm_campaign=google_jobs_apply&utm_source=google_jobs_apply&utm_medium=organic","job_apply_is_direct":false,"apply_options":[{"publisher":"LinkedIn Nigeria","apply_link":"https://ng.linkedin.com/jobs/view/software-engineer-python-golang-kubernetes-at-canonical-4185055524?utm_campaign=google_jobs_apply&utm_source=google_jobs_apply&utm_medium=organic","is_direct":false}],"job_description":"As a member of the Kubernetes product team, you will build the operators and addons; the former, offering complete lifecycle management of mission-critical components, and the latter, a zero-ops experience for seamlessly integrating projects into your Kubernetes.\n\nYou will gain familiarity with the latest features in Kubernetes and look to incorporate the best of open-source to bring functionality to our end-users. You will collaborate with industry peers and partners to bring the right solutions to our customers.\n\nThis is an exciting opportunity for a software engineer passionate about open source software, Linux, Golang, Python and Kubernetes.\n\nLocation: This is a remote position available in EMEA and the Americas.\n\nWhat you will focus on\n• Write high-quality code to create new features\n• Debug issues and interact with a vibrant community\n• Collaborate proactively with a distributed team\n• Work with helpful and talented engineers including experts in many fields\n• Work from home with global travel 2 to 4 weeks for internal and external events\n\nWhat we are looking for in you\n• You are a Golang developer also fluent in Python\n• You have experience with Kubernetes\n• You have strong written and verbal communication skills\n• You have a Bachelor's or equivalent in Computer Science, STEM or similar degree\n• You love technology and working with brilliant people\n\nWhat we offer you\n\nWe consider geographical location, experience, and performance in shaping compensation worldwide. We revisit compensation annually (and more often for graduates and associates) to ensure we recognise outstanding performance. In addition to base pay, we offer a performance-driven annual bonus. We provide all team members with additional benefits, which reflect our values and ideals. We balance our programs to meet local needs and ensure fairness globally.\n• Distributed work environment with twice-yearly team sprints in person\n• Personal learning and development budget of USD 2,000 per year\n• Annual compensation review\n• Recognition rewards\n• Annual holiday leave\n• Maternity and paternity leave\n• Employee Assistance Programme\n• Opportunity to travel to new locations to meet colleagues\n• Priority Pass, and travel upgrades for long haul company events\n\nAbout Canonical\n\nCanonical is a pioneering tech firm at the forefront of the global move to open source. As the company that publishes Ubuntu, one of the most important open source projects and the platform for AI, IoT and the cloud, we are changing the world on a daily basis. We recruit on a global basis and set a very high standard for people joining the company. We expect excellence - in order to succeed, we need to be the best at what we do. Canonical has been a remote-first company since its inception in 2004. Working here is a step into the future, and will challenge you to think differently, work smarter, learn new skills, and raise your game.\n\nCanonical is an equal opportunity employer\n\nWe are proud to foster a workplace free from discrimination. Diversity of experience, perspectives, and background create a better work environment and better products. Whatever your identity, we will give your application fair consideration.","job_is_remote":false,"job_posted_at":"13 days ago","job_posted_at_timestamp":1741996800,"job_posted_at_datetime_utc":"2025-03-15T00:00:00.000Z","job_location":"Lagos","job_city":"Lagos","job_state":"Lagos","job_country":"NG","job_latitude":6.5243793,"job_longitude":3.3792057,"job_benefits":null,"job_google_link":"https://www.google.com/search?q=jobs&gl=ng&hl=en&udm=8#vhid=vt%3D20/docid%3DL1WPUgTztny5rIYDAAAAAA%3D%3D&vssid=jobs-detail-viewer","job_salary":null,"job_min_salary":null,"job_max_salary":null,"job_salary_period":null,"job_highlights":{},"job_onet_soc":"15113200","job_onet_job_zone":"4"},{"job_id":"sBb7JRN5VrNDH6hfAAAAAA==","job_title":"C, Golang Software Engineer working on dqlite, a Raft extension for SQLite","employer_name":"Canonical","employer_logo":"https://encrypted-tbn0.gstatic.com/images?q=tbn:ANd9GcTN1rp9LyuqGEsp4IjSXeT87xSmDDw64mG1SWLF&s=0","employer_website":"https://canonical.com","job_publisher":"LinkedIn","job_employment_type":"Full-time","job_employment_types":["FULLTIME"],"job_apply_link":"https://ng.linkedin.com/jobs/view/c-golang-software-engineer-working-on-dqlite-a-raft-extension-for-sqlite-at-canonical-4185052794?utm_campaign=google_jobs_apply&utm_source=google_jobs_apply&utm_medium=organic","job_apply_is_direct":false,"apply_options":[{"publisher":"LinkedIn","apply_link":"https://ng.linkedin.com/jobs/view/c-golang-software-engineer-working-on-dqlite-a-raft-extension-for-sqlite-at-canonical-4185052794?utm_campaign=google_jobs_apply&utm_source=google_jobs_apply&utm_medium=organic","is_direct":false}],"job_description":"We are hiring a software developer to focus on dqlite, our distributed SQLite database which uses our own Raft library for establishing consensus and replication. Dqlite is available as a pure C library or through a Go package that we also maintain, and we intend to provide bindings for Python and other languages.\n\nYou will design and implement enhancements to the libraft, dqlite and go-dqlite components which we consume in MicroK8s, LXD and other projects. Work includes development in those pieces of software as well as responding to issues and user inquiries.\n\nThis is an excellent opportunity for someone who wants to have a meaningful impact on modern computing technologies. Canonical offers a fast-paced team environment and a career full of learning and development opportunities.\n\nLocation: This is a remote position available in EMEA\n\nWhat you will focus on\n• Design and implement features across dqlite\n• Debug and fix issues encountered by your users\n• Improve Jepsen tests, traditional HA database automated testing and stress tests\n• Participate in our engineering process through code and architectural review\n• Engage with the open source community and commercial partners\n\nWhat we are looking for in you\n• Experience with distributed systems (preferably with Raft)\n• Good C programming experience\n• Solid understanding of asynchronous programming and concurrency patterns a plus\n• Capacity to learn quickly about new systems and techniques\n• Strong written and verbal communication skills\n• Bachelor's or equivalent in Computer Science, STEM or similar degree\n\nWhat we offer you\n\nWe consider geographical location, experience, and performance in shaping compensation worldwide. We revisit compensation annually (and more often for graduates and associates) to ensure we recognise outstanding performance. In addition to base pay, we offer a performance-driven annual bonus. We provide all team members with additional benefits, which reflect our values and ideals. We balance our programs to meet local needs and ensure fairness globally.\n• Distributed work environment with twice-yearly team sprints in person\n• Personal learning and development budget of USD 2,000 per year\n• Annual compensation review\n• Recognition rewards\n• Annual holiday leave\n• Maternity and paternity leave\n• Employee Assistance Programme\n• Opportunity to travel to new locations to meet colleagues\n• Priority Pass, and travel upgrades for long haul company events\n\nAbout Canonical\n\nCanonical is a pioneering tech firm at the forefront of the global move to open source. As the company that publishes Ubuntu, one of the most important open source projects and the platform for AI, IoT and the cloud, we are changing the world on a daily basis. We recruit on a global basis and set a very high standard for people joining the company. We expect excellence - in order to succeed, we need to be the best at what we do. Canonical has been a remote-first company since its inception in 2004. Working here is a step into the future, and will challenge you to think differently, work smarter, learn new skills, and raise your game.\n\nCanonical is an equal opportunity employer\n\nWe are proud to foster a workplace free from discrimination. Diversity of experience, perspectives, and background create a better work environment and better products. Whatever your identity, we will give your application fair consideration.","job_is_remote":false,"job_posted_at":"13 days ago","job_posted_at_timestamp":1741996800,"job_posted_at_datetime_utc":"2025-03-15T00:00:00.000Z","job_location":"Lagos","job_city":"Lagos","job_state":"Lagos","job_country":"NG","job_latitude":6.5243793,"job_longitude":3.3792057,"job_benefits":null,"job_google_link":"https://www.google.com/search?q=jobs&gl=ng&hl=en&udm=8#vhid=vt%3D20/docid%3DsBb7JRN5VrNDH6hfAAAAAA%3D%3D&vssid=jobs-detail-viewer","job_salary":null,"job_min_salary":null,"job_max_salary":null,"job_salary_period":null,"job_highlights":{},"job_onet_soc":"15113200","job_onet_job_zone":"4"},{"job_id":"5vh3wMvTFikPwXFNAAAAAA==","job_title":"Senior Golang Developer (Vendor Portal)+Acronis","employer_name":"Acronis","employer_logo":null,"employer_website":"https://www.acronis.com","job_publisher":"BetaJob","job_employment_type":"Full-time","job_employment_types":["FULLTIME"],"job_apply_link":"https://betajob.com.ng/senior-golang-developer-vendor-portal-acronis/19533?utm_campaign=google_jobs_apply&utm_source=google_jobs_apply&utm_medium=organic","job_apply_is_direct":true,"apply_options":[{"publisher":"BetaJob","apply_link":"https://betajob.com.ng/senior-golang-developer-vendor-portal-acronis/19533?utm_campaign=google_jobs_apply&utm_source=google_jobs_apply&utm_medium=organic","is_direct":true}],"job_description":"Location: Abuja, Nigeria Job Description We are looking for skilled and motivated Senior Go Developer who, along with our excellent and modern software development team, will be responsible for working on the Vendor Portal product. This is an individual contributor position that will be responsible for the development of backend services in Go. Every member of our “A-Team” has an instrumental role and impact on the success of Acronis’ innovative and growing business, so we are looking for someone who enjoys working in dynamic, global teams and thrives in a fast-paced and rapidly changing work environment. Just like everyone at Acronis, the ideal candidate will embody all of our company values: responsive, alert, detail-oriented, makes decisions, and never gives up. Responsibilites What you'll do: Designing and developing scalable, robust, testable, efficient, and easily maintainable code in Go Owning and maintaining backend components part of a microservice architecture Implementing designs, unit tests, debugging and integrating code, performing code reviews Collaborating with PMs, QA, Architects and other stakeholders Taking part of the whole Software Development Life Cycle Mentoring more junior colleagues and helping them grow professionally. Experience & Qualifications What you bring: 5+ years of experience writing well-designed, high-quality production code in Go, C++ or other compiled languages Experience with scalable applications with microservice architectures Knowledge of software engineering principles: standard algorithms, data structures, multi-threading and concurrency Knowledge of CI/CD systems is a plus Understanding of networking is an advantage Fluent English Application Closing Date Not Specified. How to Apply Interested and qualified candidates should: Click here to apply online","job_is_remote":false,"job_posted_at":null,"job_posted_at_timestamp":null,"job_posted_at_datetime_utc":null,"job_location":"Abuja","job_city":"Abuja","job_state":"Federal Capital Territory","job_country":"NG","job_latitude":9.0562646,"job_longitude":7.4985259,"job_benefits":null,"job_google_link":"https://www.google.com/search?q=jobs&gl=ng&hl=en&udm=8#vhid=vt%3D20/docid%3D5vh3wMvTFikPwXFNAAAAAA%3D%3D&vssid=jobs-detail-viewer","job_salary":null,"job_min_salary":null,"job_max_salary":null,"job_salary_period":null,"job_highlights":{},"job_onet_soc":"15113200","job_onet_job_zone":"4"},{"job_id":"x9A4QT9_5vf-zXbxAAAAAA==","job_title":"GO-Lang Backend Developer at Apex Network Limited","employer_name":"ListingAPI-2","employer_logo":"https://encrypted-tbn0.gstatic.com/images?q=tbn:ANd9GcTwAYTaqXTFn6sFstWcXn5GdW66TKnQjfWf_DBC&s=0","employer_website":null,"job_publisher":"MyJobAlly.Com","job_employment_type":"Full-time","job_employment_types":["FULLTIME"],"job_apply_link":"https://www.myjobally.com/job/go-lang-backend-developer-at-apex-network-limited/?utm_campaign=google_jobs_apply&utm_source=google_jobs_apply&utm_medium=organic","job_apply_is_direct":false,"apply_options":[{"publisher":"MyJobAlly.Com","apply_link":"https://www.myjobally.com/job/go-lang-backend-developer-at-apex-network-limited/?utm_campaign=google_jobs_apply&utm_source=google_jobs_apply&utm_medium=organic","is_direct":false}],"job_description":"Apex Network is a Financial servicing firm, where anyone anywhere can easily and securely transact Bitcoin, which is the future of Money and a catalyst for creating and open financial system in Africa and the World.\n\nWe are recruiting to fill the position below:\n\nJob Title: GO-Lang Backend Developer\n\nLocation: Lekki, Lagos\n\nJob type: Full-Time\n\nDepartment: Information Technology\n\nJob Description\n• We are sourcing for a Golang developer, who will help in building a optimised, scalable, and modular software using required technologies.\n• You will be tasked developing and coding back-end components and connecting applications to other web services.\n\nWhat you will do looks like\n• Structure our user interface with React and ensure REST API access is available for enterprise-grade finance customers on-demand\n• Collaborate with other technical staff to ensure consistent and smooth DevOps workflows.\n• Choose and implement other libraries that will optimise performance without sacrificing security and base functionality\n• Manage multiple projects within reasonable design specifications and budget restrictions\n• QA design for errors\n• Implement feedback and changes whenever possible\n• Create visualisation that convey accurate messaging for the project.\n• Writing scalable, robust,, testable, efficient, and easily maintainable code\n• Translating software requirements into stable, working, high performance software\n• Playing a key role in architectural and design decisions, building toward an efficient micro services distributed architecture.\n\nWhat you should have looks like\n• Minimum of two years experience working in programming or information technology\n• Excellent written and verbal communication skills\n• Attention to detail..\n• Strong knowledge of Go programming language, paradigms, constructs, and idioms\n• Knowledge of common Goroutine and channel patterns\n• Experience with the full site of Go frameworks and tools, including:\n• Dependency management tools such as Godep, Sltr, etc.\n• Go’s templating language\n• Go’s code generation tools, such as Stringer\n• Popular Go web frameworks, such as Revel\n• Router packages, such as Gorilla Mux\n• Ability to write clean and effective Godoc comments\n• Other programming language experience such as ( LARAVEL, JAVASCRIPT etcetera.)\n• Strong analytical skills\n• Time management and organisational skills\n• Knowledge of Go templating, common frameworks, and tools\n• Experience working with a team.\n\nApplication Closing Date\n\nNot Specified.\n\nHow to Apply\n\nInterested and qualified candidates should:\n\nClick here to apply online","job_is_remote":false,"job_posted_at":null,"job_posted_at_timestamp":null,"job_posted_at_datetime_utc":null,"job_location":"Ibeju","job_city":"Ibeju","job_state":"Lagos","job_country":"NG","job_latitude":6.484799799999999,"job_longitude":3.8897149,"job_benefits":null,"job_google_link":"https://www.google.com/search?q=jobs&gl=ng&hl=en&udm=8#vhid=vt%3D20/docid%3Dx9A4QT9_5vf-zXbxAAAAAA%3D%3D&vssid=jobs-detail-viewer","job_salary":null,"job_min_salary":null,"job_max_salary":null,"job_salary_period":null,"job_highlights":{},"job_onet_soc":"15113200","job_onet_job_zone":"4"},{"job_id":"-gbanm94-BHcIOzRAAAAAA==","job_title":"Engineering Manager - Public Cloud, Python, Golang","employer_name":"Canonical","employer_logo":"https://encrypted-tbn0.gstatic.com/images?q=tbn:ANd9GcTN1rp9LyuqGEsp4IjSXeT87xSmDDw64mG1SWLF&s=0","employer_website":"https://canonical.com","job_publisher":"LinkedIn","job_employment_type":"Full-time","job_employment_types":["FULLTIME"],"job_apply_link":"https://ng.linkedin.com/jobs/view/engineering-manager-public-cloud-python-golang-at-canonical-4184850294?utm_campaign=google_jobs_apply&utm_source=google_jobs_apply&utm_medium=organic","job_apply_is_direct":false,"apply_options":[{"publisher":"LinkedIn","apply_link":"https://ng.linkedin.com/jobs/view/engineering-manager-public-cloud-python-golang-at-canonical-4184850294?utm_campaign=google_jobs_apply&utm_source=google_jobs_apply&utm_medium=organic","is_direct":false}],"job_description":"Canonical Ubuntu is the most widely used OS for public cloud instances across every major public cloud. Our team builds, tests, and publishes the base Ubuntu images used by millions to ensure optimal performance and security in their cloud estate. We aim to deliver the very best public cloud VM experience, as well as specialized images for specific purposes on each cloud.\n\nWe work closely with Amazon, Microsoft, Google and other world-class cloud partners to optimise Ubuntu for their infrastructure. Our goal is to celebrate and enable their particular points of differentiation on their clouds, while also ensure a common operating experience for their users.\n\nAs an engineering manager you need to bring both technical and management skills to the leadership of your team. You will also need to represent the team in direct partner engagement. You'll be responsible for the stability and functionality that our cloud users have come to expect. You will strive to automate the delivery of existing and new Ubuntu image products applied to all modern workloads from web servers to GPU-aided AI for servers, VM's and containers.\n\nAs an engineering manager at Canonical your primary responsibility is to the people you support: ensuring that they are growing as engineers, doing valuable work, and generally having a great time at Canonical. As a lead for strong engineers, technical leadership and a solid background in software development is a must, so that you're able to challenge and grow your team members. You will have the opportunity to influence the culture, facilitate technical delivery, and work with your team on strategy and execution.\n\nWe work in Python and Golang, and expect engineering managers to be fluent in the language, architecture and components that their team is building with. Code reviews and architectural leadership are part of the job. As manager, the commitment to healthy engineering practices, documentation, quality and performance optimisation are equally important technical responsibilities, as is the requirement for fair and clear management, and the obligation to ensure a high performing team.\n\nWhat you'll do\n• Build and lead a team of engineers in your and similar timezones\n• Develop talent through coaching, mentoring, feedback and hands-on career development\n• Demonstrate sound engineering principles and directly contribute toward your team's goals\n• Set and manage expectations with other engineering teams, management, and external stakeholders\n• Lead modern, agile software development practices\n• Ensure a healthy, collaborative engineering culture in line with the company values\n• Be an active part of the leadership team and collaborate with other leaders in the organisation\n• Build automated, highly reliable image delivery, testing and publication pipelines\n• Engage with many other teams at Canonical, as well as the open source community and commercial partners\n• Work from home with global travel up to 15% for internal and external events\n\nWho you are\n• You love to mentor, develop and grow people, and have a track record of doing it\n• You are knowledgeable and passionate about software development\n• You are focused on success and the delivery of timely, high quality software\n• You have experience and commitment to agile development methodologies\n• You have a Bachelor's or equivalent in Computer Science, STEM or similar degree\n• Software development experience in Python or Golang\n• Effective written and verbal communication skills\n• Practical experience with at least one of Microsoft Azure, Google Cloud, or AWS\n\nWhat we offer you\n\nWe consider geographical location, experience, and performance in shaping compensation worldwide. We revisit compensation annually (and more often for graduates and associates) to ensure we recognise outstanding performance. In addition to base pay, we offer a performance-driven annual bonus. We provide all team members with additional benefits, which reflect our values and ideals. We balance our programs to meet local needs and ensure fairness globally.\n• Distributed work environment with twice-yearly team sprints in person\n• Personal learning and development budget of USD 2,000 per year\n• Annual compensation review\n• Recognition rewards\n• Annual holiday leave\n• Maternity and paternity leave\n• Employee Assistance Programme\n• Opportunity to travel to new locations to meet colleagues\n• Priority Pass, and travel upgrades for long haul company events\n\nAbout Canonical\n\nCanonical is a pioneering tech firm at the forefront of the global move to open source. As the company that publishes Ubuntu, one of the most important open source projects and the platform for AI, IoT and the cloud, we are changing the world on a daily basis. We recruit on a global basis and set a very high standard for people joining the company. We expect excellence - in order to succeed, we need to be the best at what we do. Canonical has been a remote-first company since its inception in 2004. Working here is a step into the future, and will challenge you to think differently, work smarter, learn new skills, and raise your game.\n\nCanonical is an equal opportunity employer\n\nWe are proud to foster a workplace free from discrimination. Diversity of experience, perspectives, and background create a better work environment and better products. Whatever your identity, we will give your application fair consideration.","job_is_remote":false,"job_posted_at":"14 days ago","job_posted_at_timestamp":1741910400,"job_posted_at_datetime_utc":"2025-03-14T00:00:00.000Z","job_location":"Lagos","job_city":"Lagos","job_state":"Lagos","job_country":"NG","job_latitude":6.5243793,"job_longitude":3.3792057,"job_benefits":null,"job_google_link":"https://www.google.com/search?q=jobs&gl=ng&hl=en&udm=8#vhid=vt%3D20/docid%3D-gbanm94-BHcIOzRAAAAAA%3D%3D&vssid=jobs-detail-viewer","job_salary":null,"job_min_salary":null,"job_max_salary":null,"job_salary_period":null,"job_highlights":{},"job_onet_soc":"11904100","job_onet_job_zone":"5"},{"job_id":"Tok3sa9N6X6hrNjhAAAAAA==","job_title":"Juju Software Engineer (Go)","employer_name":"Canonical","employer_logo":"https://encrypted-tbn0.gstatic.com/images?q=tbn:ANd9GcTN1rp9LyuqGEsp4IjSXeT87xSmDDw64mG1SWLF&s=0","employer_website":"https://canonical.com","job_publisher":"LinkedIn","job_employment_type":"Full-time","job_employment_types":["FULLTIME"],"job_apply_link":"https://ng.linkedin.com/jobs/view/juju-software-engineer-go-at-canonical-4127923384?utm_campaign=google_jobs_apply&utm_source=google_jobs_apply&utm_medium=organic","job_apply_is_direct":false,"apply_options":[{"publisher":"LinkedIn","apply_link":"https://ng.linkedin.com/jobs/view/juju-software-engineer-go-at-canonical-4127923384?utm_campaign=google_jobs_apply&utm_source=google_jobs_apply&utm_medium=organic","is_direct":false}],"job_description":"The role of a Software Engineer at Canonical\n\nAs a software engineer on the team, you'll be contributing to the development of Juju, a large open-source Go project that powers complex distributed software systems across the world.\n\nJuju is the engine behind model-driven operations, providing a means to operate complex software on public cloud, private cloud, Kubernetes, and bare-metal. Combined with the Ops framework, Juju provides a complete solution for applications and infrastructure management.\n\nMany internal and external teams depend on Juju to deliver their products and services - from Canonical Managed Solutions, our OpenStack and cloud delivery teams, to Fortune 500 companies.\n\nLocation: This is a Globally remote role.\n\nWhat your day will look like\n• Contribute to the design, delivery, and support of features in a highly concurrent, highly distributed system that drives cloud automation and software operations at scale.\n• Collaborate proactively with a distributed team\n• Debug issues and interact with upstream communities publicly\n• Work with helpful and talented engineers including experts in many fields\n• Discuss ideas and collaborate on finding good solutions\n• Work from home with global travel for 2 to 4 weeks per year for internal and external events\n\nWhat we are looking for in you\n• Experience developing software using Go.\n• Excellent communication skills in the English language, both verbal and written, especially in online environments\n• An exceptional academic track record from both high school and preferably university\n• Willingness to travel up to 4 times a year for internal events\n\nAdditional skills that you might also bring\n\nThe following skills may be helpful to you in the role, but we don't expect everyone to bring all of them.\n• Hands-on experience developing highly concurrent distributed systems\n• Experience with container technologies (Docker, LXD, Kubernetes, etc.)\n• Solid networking background and experience\n• Experience with agile software development methodologies\n• Experience in the Linux and open-source software world\n• Experience with configuration management software (Ansible, Chef, Puppet, et al.)\n• Working knowledge of cloud computing\n• Experience with software packaging (Debian, snaps)\n• Programming with, and operating, SQL and NoSQL databases\n• Experience working on a distributed team on an open source project -- even if that is community open source contributions.\n• Demonstrated track record of Open Source contributions\n• Prior experience developing plugins for Terraform\n\nWhat we offer you\n\nWe consider geographical location, experience, and performance in shaping compensation worldwide. We revisit compensation annually (and more often for graduates and associates) to ensure we recognise outstanding performance. In addition to base pay, we offer a performance-driven annual bonus. We provide all team members with additional benefits, which reflect our values and ideals. We balance our programs to meet local needs and ensure fairness globally.\n• Distributed work environment with twice-yearly team sprints in person - we've been working remotely since 2004!\n• Personal learning and development budget of USD 2,000 per year\n• Annual compensation review\n• Recognition rewards\n• Annual holiday leave\n• Maternity and paternity leave\n• Employee Assistance Programme\n• Opportunity to travel to new locations to meet colleagues from your team and others\n• Priority Pass for travel and travel upgrades for long haul company events\n\nAbout Canonical\n\nCanonical is a pioneering tech firm that is at the forefront of the global move to open source. As the company that publishes Ubuntu, one of the most important open source projects and the platform for AI, IoT and the cloud, we are changing the world on a daily basis. We recruit on a global basis and set a very high standard for people joining the company. We expect excellence - in order to succeed, we need to be the best at what we do.\n\nCanonical has been a remote-first company since its inception in 2004. Work at Canonical is a step into the future, and will challenge you to think differently, work smarter, learn new skills, and raise your game. Canonical provides a unique window into the world of 21st-century digital business.\n\nCanonical is an equal opportunity employer\n\nWe are proud to foster a workplace free from discrimination. Diversity of experience, perspectives, and background create a better work environment and better products. Whatever your identity, we will give your application fair consideration.","job_is_remote":false,"job_posted_at":null,"job_posted_at_timestamp":null,"job_posted_at_datetime_utc":null,"job_location":"Lagos","job_city":"Lagos","job_state":"Lagos","job_country":"NG","job_latitude":6.5243793,"job_longitude":3.3792057,"job_benefits":null,"job_google_link":"https://www.google.com/search?q=jobs&gl=ng&hl=en&udm=8#vhid=vt%3D20/docid%3DTok3sa9N6X6hrNjhAAAAAA%3D%3D&vssid=jobs-detail-viewer","job_salary":null,"job_min_salary":null,"job_max_salary":null,"job_salary_period":null,"job_highlights":{},"job_onet_soc":"15113300","job_onet_job_zone":"4"},{"job_id":"a8sQkXOgI441fawpAAAAAA==","job_title":"Linux devices software engineer - snapd","employer_name":"Canonical","employer_logo":"https://encrypted-tbn0.gstatic.com/images?q=tbn:ANd9GcTN1rp9LyuqGEsp4IjSXeT87xSmDDw64mG1SWLF&s=0","employer_website":"https://canonical.com","job_publisher":"LinkedIn Nigeria","job_employment_type":"Full-time","job_employment_types":["FULLTIME"],"job_apply_link":"https://ng.linkedin.com/jobs/view/linux-devices-software-engineer-snapd-at-canonical-4157964235?utm_campaign=google_jobs_apply&utm_source=google_jobs_apply&utm_medium=organic","job_apply_is_direct":false,"apply_options":[{"publisher":"LinkedIn Nigeria","apply_link":"https://ng.linkedin.com/jobs/view/linux-devices-software-engineer-snapd-at-canonical-4157964235?utm_campaign=google_jobs_apply&utm_source=google_jobs_apply&utm_medium=organic","is_direct":false}],"job_description":"Work on mission-critical Golang code, focused on software delivery, containers, security sandboxing, telemetry and device management, as a software engineer on our SnapD team.\n\nSnaps are next-generation software packaging and delivery for Linux. They are designed for safety, security and robustness, with application-specific confinement of containers optimised for IoT devices, desktops and servers. Our goal is that snaps work across multiple Linux flavors to ensure that publishers have the simplest way to reach the whole Linux world.\n\nThis role requires an obsession with quality and performance, for work at the heart of the operating system. It also requires an interest in the software publishing and consumption experience. Applicants should be passionate about open source software development. We value collaboration, peer reviews, good unit/integration testing and maintainable code. General knowledge and experience with Linux as a developer platform is required. Having previous experience with Golang is very nice to have.\n\nWhat you'll do\n• Collaborate proactively with a distributed team\n• Write high quality code to create new features\n• Debug Linux system level issues and produce high quality code to fix them\n• Review code produced by other engineers\n• Discuss ideas and collaborate on finding good solutions\n• Obsess over how to achieve robustness despite unexpected events like power outages\n• Work from home with global travel for up to two weeks, twice a year\n\nWho you are\n• You love technology and working with brilliant people\n• You are curious, flexible, articulate, and accountable\n• You value soft skills, are thoughtful and self-motivated\n• You have a Bachelor's or equivalent in Computer Science, STEM or similar degree\n• You have professional software development experience using Go, Python, C, or C++\n• You know Linux system-level fundamentals, e.g. cgroups, namespaces, apparmor\n• Commitment to software testing, code reviews and maintainable code\n\nAbout Canonical\n\nCanonical is a growing, international software company that works with the open-source community to deliver Ubuntu. Our services help businesses worldwide to reduce costs, improve efficiency and enhance security with Ubuntu. Canonical is a unique tech company - global, remote-first, open source, with 1100 professionals across 70 countries - we want to be the world's best, not biggest, global software company. With almost every team remote by default, Canonical sets the pace on the 21st-century digital workplace.\n• Work from home\n• Learning and development allowances\n• Competitive Salary\n• Annual compensation review\n• Recognition rewards\n• Generous annual leave\n• Paid maternity, paternity and sick leave\n• Priority Pass for travel\n• Exposure to international business and technology\n\nWe are proud to foster a workplace free from discrimination. Diversity of experience, perspectives, and background create a better work environment and better products. Whatever your identity, we will give your application fair consideration.","job_is_remote":false,"job_posted_at":null,"job_posted_at_timestamp":null,"job_posted_at_datetime_utc":null,"job_location":"Lagos","job_city":"Lagos","job_state":"Lagos","job_country":"NG","job_latitude":6.5243793,"job_longitude":3.3792057,"job_benefits":null,"job_google_link":"https://www.google.com/search?q=jobs&gl=ng&hl=en&udm=8#vhid=vt%3D20/docid%3Da8sQkXOgI441fawpAAAAAA%3D%3D&vssid=jobs-detail-viewer","job_salary":null,"job_min_salary":null,"job_max_salary":null,"job_salary_period":null,"job_highlights":{},"job_onet_soc":"15113300","job_onet_job_zone":"4"}]}